pysynclient/__init__.py
pysynclient/client/server_paths.py
pysynclient-0.1.1.dist-info/LICENSE
pysynclient-0.1.1.dist-info/METADATA
pysynclient-0.1.1.dist-info/WHEEL
pysynclient-0.1.1.dist-info/RECORD
