Metadata-Version: 2.1
Name: pysynclient
Version: 0.1.1
Summary: Automatically detects the location of the synology drive client folders and returns its parent location.
License: GPL-3.0 license
Author: Dominik Braun
Author-email: dome.braun@fau.de
Requires-Python: >=3.10
Classifier: License :: Other/Proprietary License
Classifier: Programming Language :: Python :: 3
Classifier: Programming Language :: Python :: 3.10
Classifier: Programming Language :: Python :: 3.11
Requires-Dist: pywin32 (>=308,<309)
